scooby/__init__.py
scooby/__main__.py
scooby/knowledge.py
scooby/py.typed
scooby/report.py
scooby/tracker.py
scooby/version.py
scooby-0.10.2.dist-info/LICENSE
scooby-0.10.2.dist-info/METADATA
scooby-0.10.2.dist-info/WHEEL
scooby-0.10.2.dist-info/entry_points.txt
scooby-0.10.2.dist-info/top_level.txt
scooby-0.10.2.dist-info/RECORD
