Metadata-Version: 2.1
Name: scooby
Version: 0.10.2
Summary: A Great Dane turned Python environment detective
Home-page: https://github.com/banesullivan/scooby
Author: Dieter Werthmüller, Bane Sullivan, Alex Kaszynski, and contributors
Author-email: info@pyvista.org
License: UNKNOWN
Platform: UNKNOWN
Classifier: Programming Language :: Python
Classifier: License :: OSI Approved :: MIT License
Classifier: Operating System :: OS Independent
Classifier: Intended Audience :: Science/Research
Classifier: Natural Language :: English
Requires-Python: >=3.8
Provides-Extra: cpu
License-File: LICENSE
